{
  "config_version": "2.0.12",
  "config_datetime": "2026-01-13_20-40-51",
  "general": {
    "disable_all_structures": false,
    "prevent_structure_overlap": true,
    "enable_global_spacing_and_separation_modifier": true,
    "global_spacing_and_separation_modifier": 3.0
  },
  "structure_namespaces": [
    {
      "name": "global",
      "is_disabled": false,
      "override_global_distance_from_world_center": false,
      "min_distance_from_world_center": 1024,
      "max_distance_from_world_center": 0
    },
    {
      "name": "incendium",
      "is_disabled": false,
      "override_global_distance_from_world_center": true,
      "min_distance_from_world_center": 0,
      "max_distance_from_world_center": 0
    },
    {
      "name": "supplementaries",
      "is_disabled": false,
      "override_global_distance_from_world_center": true,
      "min_distance_from_world_center": 512,
      "max_distance_from_world_center": 0
    }
  ],
  "structures": [
    {
      "name": "u_sea:lighthouse",
      "is_disabled": true,
      "whitelisted_biomes": [],
      "blacklisted_biomes": [],
      "step": "surface_structures",
      "terrain_adaptation": "beard_thin"
    },
    {
      "name": "u_sea:raft/cold/cone_tide_breaker",
      "is_disabled": true,
      "whitelisted_biomes": [],
      "blacklisted_biomes": [],
      "step": "surface_structures",
      "terrain_adaptation": "none"
    },
    {
      "name": "u_sea:raft/cold/tide_breaker",
      "is_disabled": true,
      "whitelisted_biomes": [],
      "blacklisted_biomes": [],
      "step": "surface_structures",
      "terrain_adaptation": "none"
    },
    {
      "name": "u_sea:raft/cold/wide_tide_breaker",
      "is_disabled": true,
      "whitelisted_biomes": [],
      "blacklisted_biomes": [],
      "step": "surface_structures",
      "terrain_adaptation": "none"
    },
    {
      "name": "u_sea:raft/temperate/beam",
      "is_disabled": true,
      "whitelisted_biomes": [],
      "blacklisted_biomes": [],
      "step": "surface_structures",
      "terrain_adaptation": "none"
    },
    {
      "name": "u_sea:raft/temperate/box",
      "is_disabled": true,
      "whitelisted_biomes": [],
      "blacklisted_biomes": [],
      "step": "surface_structures",
      "terrain_adaptation": "none"
    },
    {
      "name": "u_sea:raft/temperate/grid",
      "is_disabled": true,
      "whitelisted_biomes": [],
      "blacklisted_biomes": [],
      "step": "surface_structures",
      "terrain_adaptation": "none"
    },
    {
      "name": "u_sea:raft/warm/cone_skipper",
      "is_disabled": true,
      "whitelisted_biomes": [],
      "blacklisted_biomes": [],
      "step": "surface_structures",
      "terrain_adaptation": "none"
    },
    {
      "name": "u_sea:raft/warm/skipper",
      "is_disabled": true,
      "whitelisted_biomes": [],
      "blacklisted_biomes": [],
      "step": "surface_structures",
      "terrain_adaptation": "none"
    },
    {
      "name": "u_sea:ship/cove",
      "is_disabled": true,
      "whitelisted_biomes": [],
      "blacklisted_biomes": [],
      "step": "surface_structures",
      "terrain_adaptation": "none"
    },
    {
      "name": "u_sea:ship/hopper",
      "is_disabled": true,
      "whitelisted_biomes": [],
      "blacklisted_biomes": [],
      "step": "surface_structures",
      "terrain_adaptation": "none"
    }
  ],
  "structure_sets": [
    {
      "spacing": 30,
      "separation": 16,
      "name": "incendium:greater_structures",
      "salt": 69420,
      "frequency": 1.0,
      "override_global_spacing_and_separation_modifier": true
    },
    {
      "spacing": 20,
      "separation": 12,
      "name": "incendium:lesser_structures",
      "salt": 399125,
      "frequency": 1.0,
      "override_global_spacing_and_separation_modifier": true
    },
    {
      "spacing": 35,
      "separation": 11,
      "name": "minecraft:end_cities",
      "salt": 10387313,
      "frequency": 1.0,
      "override_global_spacing_and_separation_modifier": true
    },
    {
      "spacing": 16,
      "separation": 8,
      "name": "minecraft:nether_complexes",
      "salt": 30084232,
      "frequency": 1.0,
      "override_global_spacing_and_separation_modifier": true
    },
    {
      "spacing": 2,
      "separation": 1,
      "name": "minecraft:nether_fossils",
      "salt": 14357921,
      "frequency": 1.0,
      "override_global_spacing_and_separation_modifier": true
    },
    {
      "spacing": 24,
      "separation": 4,
      "name": "minecraft:shipwrecks",
      "salt": 165745295,
      "frequency": 0.5,
      "override_global_spacing_and_separation_modifier": false
    },
    {
      "spacing": 75,
      "separation": 55,
      "name": "minecraft:villages",
      "salt": 213742069,
      "frequency": 0.6,
      "override_global_spacing_and_separation_modifier": false
    },
    {
      "spacing": 19,
      "separation": 10,
      "name": "supplementaries:way_signs",
      "salt": 431041527,
      "frequency": 1.0,
      "override_global_spacing_and_separation_modifier": true
    }
  ]
}